{
  "id": "clementine",
  "agency": "NASA",
  "agency_full": "U.S. Naval Research Laboratory / NASA (joint Department of Defense-NASA mission)",
  "sector": "gov",
  "dest": "MOON",
  "color": "#0B3D91",
  "year": 1994,
  "status": "FLOWN",
  "departure_date": "1994-01-25",
  "arrival_date": "1994-02-19",
  "transit_days": 25,
  "vehicle": "Titan II G",
  "payload": "424 kg dry mass; 1690 kg launch mass with propellant",
  "delta_v": "~3.5 km/s",
  "data_quality": "good",
  "credit": "© U.S. NRL / NASA — declassified DoD mission. Purpose: technology demonstration for SDI, mapped Moon as bonus. Found first hints of water ice at lunar poles.",
  "links": [
    {
      "l": "Clementine — Wikipedia",
      "u": "https://en.wikipedia.org/wiki/Clementine_(spacecraft)",
      "t": "intro"
    },
    {
      "l": "Clementine (NSSDCA)",
      "u": "https://nssdc.gsfc.nasa.gov/nmc/spacecraft/display.action?id=1994-004A",
      "t": "core"
    }
  ],
  "flight_data_quality": "measured",
  "flight": {
    "launch": {
      "vehicle_stage": "Titan II Star-37 upper stage",
      "mass_at_tli_kg": 1690,
      "source": "NASA NSSDCA Clementine archive; NRL Clementine Mission Report (1994)"
    },
    "cruise": {
      "tcm_count": 3,
      "source": "NRL Clementine Mission Report (1994); used phasing loops + lunar gravity assist"
    },
    "arrival": {
      "v_infinity_km_s": 0.85,
      "periapsis_km": 425,
      "inclination_deg": 90.0,
      "orbit_insertion_dv_km_s": 0.56,
      "source": "NRL Clementine Mission Report (1994); polar mapping orbit"
    },
    "totals": {
      "total_dv_km_s": 3.5,
      "source": "NRL Clementine Mission Report (1994)"
    },
    "events": [
      {
        "met_days": 0,
        "type": "launch"
      },
      {
        "met_days": 0.5,
        "type": "tli_or_tmi"
      },
      {
        "met_days": 7,
        "type": "tcm"
      },
      {
        "met_days": 7.24,
        "type": "tcm"
      },
      {
        "met_days": 12.75,
        "type": "tcm"
      },
      {
        "met_days": 25,
        "type": "arrival"
      },
      {
        "met_days": 25.05,
        "type": "edl_or_oi"
      }
    ]
  }
}
